logviz/__init__.py
logviz/constants.py
logviz/defaults.py
logviz/formatters.py
logviz/logger.py
logviz/styles.py
logviz-0.2.0.dist-info/METADATA
logviz-0.2.0.dist-info/WHEEL
logviz-0.2.0.dist-info/top_level.txt
logviz-0.2.0.dist-info/RECORD
