Metadata-Version: 2.1
Name: logviz
Version: 0.2.0
Summary: A log visualization tool
Home-page: https://github.com/okwesi/LogViz
Author: Owusu Kenneth
Author-email: Your Name <you@example.com>
License: MIT
Project-URL: Homepage, https://your-project-homepage.com
Classifier: Programming Language :: Python :: 3
Classifier: License :: OSI Approved :: MIT License
Classifier: Operating System :: OS Independent
Requires-Python: >=3.8
